ffzf-0.2.6.dist-info/METADATA
ffzf-0.2.6.dist-info/WHEEL
ffzf-0.2.6.dist-info/license_files/LICENSE
ffzf/__init__.py
ffzf/__init__.pyi
ffzf/py.typed
ffzf/ffzf.cpython-310-x86_64-linux-gnu.so
ffzf-0.2.6.dist-info/RECORD
